ids_es_json_generator/__init__.py
ids_es_json_generator/__main__.py
ids_es_json_generator/generator.py
ts_ids_es_json_generator-1.0.1.dist-info/LICENSE
ts_ids_es_json_generator-1.0.1.dist-info/METADATA
ts_ids_es_json_generator-1.0.1.dist-info/WHEEL
ts_ids_es_json_generator-1.0.1.dist-info/top_level.txt
ts_ids_es_json_generator-1.0.1.dist-info/RECORD
