Metadata-Version: 2.1
Name: ts-ids-es-json-generator
Version: 1.0.1
Summary: Python utility for generating elasticsearch.json from schema.json for an IDS
Home-page: https://github.com/tetrascience/ts-ids-es-json-generator
Author: tetrascience
Author-email: developers@tetrascience.com
License: Apache License 2.0
Project-URL: Tetra Developer Site, https://developers.tetrascience.com
Platform: UNKNOWN
Classifier: Programming Language :: Python :: 3
Classifier: License :: OSI Approved :: Apache Software License
Classifier: Operating System :: OS Independent
Requires-Python: >=3.7
License-File: LICENSE
Requires-Dist: jsonref (>=0.2)
Requires-Dist: pydash (>=5.0.0)
